PyTorchLayerViz/__init__.py
PyTorchLayerViz/main.py
PyTorchLayerViz-1.2.5.dist-info/LICENSE.md
PyTorchLayerViz-1.2.5.dist-info/METADATA
PyTorchLayerViz-1.2.5.dist-info/WHEEL
PyTorchLayerViz-1.2.5.dist-info/commands.txt
PyTorchLayerViz-1.2.5.dist-info/top_level.txt
PyTorchLayerViz-1.2.5.dist-info/RECORD
