Metadata-Version: 2.1
Name: PyTorchLayerViz
Version: 1.2.5
Summary: PyTorchLayerViz is a Python library that allows you to visualize the weights and feature maps of a PyTorch model.
Author: Simone Panico
Author-email: simone.panico@icloud.com
Keywords: python,pytorch,deep learning,model
License-File: LICENSE.md
Requires-Dist: torch
Requires-Dist: torchvision
Requires-Dist: pillow
Requires-Dist: matplotlib
